{
  "formPersonDetails": {
    "locator": "//form[@id='formPersonDetails']",
    "modal_locator": "",
    "buttons": {
      "add": {
        "locator": "//button[@id='addFeatureButton']",
        "expect": ""
      },
      "fields": {
        "ProfileId": {
          "locator": "//select[@id='ProfileId']",
          "type": "number",
          "required": true,
          "minlength": null,
          "maxlength": null,
          "rangelength": null,
          "minvalue": null,
          "maxvalue": null,
          "rangevalue": null,
          "expect": ""
        },
        "Feature": {
          "locator": "//select[@id='Feature']",
          "type": "select-one",
          "required": false,
          "minlength": null,
          "maxlength": null,
          "rangelength": null,
          "minvalue": null,
          "maxvalue": null,
          "rangevalue": null,
          "expect": ""
        },
        "Packages": {
          "locator": "//select[@id='Packages']",
          "type": "select-one",
          "required": false,
          "minlength": null,
          "maxlength": null,
          "rangelength": null,
          "minvalue": null,
          "maxvalue": null,
          "rangevalue": null,
          "expect": ""
        },
        "DateLive": {
          "locator": "//input[@id='DateLive']",
          "type": "date",
          "required": true,
          "minlength": null,
          "maxlength": null,
          "rangelength": null,
          "minvalue": null,
          "maxvalue": null,
          "rangevalue": null,
          "expect": ""
        }
      }
    }
  },
  "edit_in_place": {
    "buttons": {
      "changepassword": {
        "locator": "//button[@id='changePassword']",
        "expect": "//div[@aria-describedby='changePersonPasswordForm']"
      }
    },
    "fields": {
      "PIusername": {
        "locator": "//span[@id='username']",
        "type": "text",
        "required": false,
        "minlength": false,
        "maxlength": false,
        "rangelength": false,
        "minvalue": false,
        "maxvalue": false,
        "rangevalue": false,
        "expect": ""
      },
      "firstName": {
        "locator": "//span[@id='firstName']",
        "type": "text",
        "required": false,
        "minlength": false,
        "maxlength": false,
        "rangelength": false,
        "minvalue": false,
        "maxvalue": false,
        "rangevalue": false,
        "expect": ""
      },
      "lastName": {
        "locator": "//span[@id='lastName']",
        "type": "text",
        "required": false,
        "minlength": false,
        "maxlength": false,
        "rangelength": false,
        "minvalue": false,
        "maxvalue": false,
        "rangevalue": false,
        "expect": ""
      },
      "title": {
        "locator": "//span[@id='title']",
        "type": "text",
        "required": false,
        "minlength": false,
        "maxlength": false,
        "rangelength": false,
        "minvalue": false,
        "maxvalue": false,
        "rangevalue": false,
        "expect": ""
      },
      "businessEmail": {
        "locator": "//span[@id='businessEmail']",
        "type": "text",
        "required": false,
        "minlength": false,
        "maxlength": false,
        "rangelength": false,
        "minvalue": false,
        "maxvalue": false,
        "rangevalue": false,
        "expect": ""
      },
      "personalEmail": {
        "locator": "//span[@id='personalEmail']",
        "type": "text",
        "required": false,
        "minlength": false,
        "maxlength": false,
        "rangelength": false,
        "minvalue": false,
        "maxvalue": false,
        "rangevalue": false,
        "expect": ""
      },
      "cellPhone": {
        "locator": "//span[@id='cellPhone']",
        "type": "text",
        "required": false,
        "minlength": false,
        "maxlength": false,
        "rangelength": false,
        "minvalue": false,
        "maxvalue": false,
        "rangevalue": false,
        "expect": ""
      },
      "homePhone": {
        "locator": "//span[@id='homePhone']",
        "type": "text",
        "required": false,
        "minlength": false,
        "maxlength": false,
        "rangelength": false,
        "minvalue": false,
        "maxvalue": false,
        "rangevalue": false,
        "expect": ""
      },
      "personLocation": {
        "locator": "//span[@id='personLocation']",
        "type": "select-one",
        "required": false,
        "minlength": false,
        "maxlength": false,
        "rangelength": false,
        "minvalue": false,
        "maxvalue": false,
        "rangevalue": false,
        "expect": ""
      }
    }
  },
  "changePersonPassword": {
    "locator": "//div[@id='changePersonPasswordForm']//form",
    "modal_locator": "//div[@aria-describedby='changePersonPasswordForm']",
    "buttons": {
      "close": {
        "locator": "//body/div[8]/div[1]/button[1]",
        "expect": ""
      },
      "ok": {
        "locator": "//button[@id='changePersonPasswordForm_OK']",
        "expect": ""
      },
      "cancel": {
        "locator": "//button[@id='changePersonPasswordForm_Cancel']",
        "expect": ""
      }
    },
    "fields": {
      "OldPersonPassword": {
        "locator": "//input[@id='OldPersonPassword']",
        "type": "password",
        "required": true,
        "minlength": null,
        "maxlength": null,
        "rangelength": null,
        "minvalue": null,
        "maxvalue": null,
        "rangevalue": null,
        "expect": ""
      },
      "NewPersonPassword": {
        "locator": "//input[@id='NewPersonPassword']",
        "type": "password",
        "required": true,
        "minlength": 6,
        "maxlength": 16,
        "rangelength": [
          6,
          16
        ],
        "minvalue": null,
        "maxvalue": null,
        "rangevalue": null,
        "expect": ""
      },
      "ConfirmPersonPassword": {
        "locator": "//input[@id='ConfirmPersonPassword']",
        "type": "password",
        "required": true,
        "minlength": null,
        "maxlength": null,
        "rangelength": null,
        "minvalue": null,
        "maxvalue": null,
        "rangevalue": null,
        "expect": ""
      },
      "NotifyUser": {
        "locator": "//input[@id='NotifyUser']",
        "type": "checkbox",
        "required": false,
        "minlength": null,
        "maxlength": null,
        "rangelength": null,
        "minvalue": null,
        "maxvalue": null,
        "rangevalue": null,
        "expect": ""
      },
      "EmailList": {
        "locator": "//input[@id='EmailList']",
        "type": "text",
        "required": false,
        "minlength": null,
        "maxlength": null,
        "rangelength": null,
        "minvalue": null,
        "maxvalue": null,
        "rangevalue": null,
        "expect": ""
      }
    }
  }
}